rpc_qtest_swagger_client-9.1.6.dist-info/DESCRIPTION.rst
rpc_qtest_swagger_client-9.1.6.dist-info/METADATA
rpc_qtest_swagger_client-9.1.6.dist-info/RECORD
rpc_qtest_swagger_client-9.1.6.dist-info/WHEEL
rpc_qtest_swagger_client-9.1.6.dist-info/metadata.json
rpc_qtest_swagger_client-9.1.6.dist-info/top_level.txt
swagger_client/__init__.py
swagger_client/api_client.py
swagger_client/configuration.py
swagger_client/rest.py
swagger_client/apis/__init__.py
swagger_client/apis/attachment_api.py
swagger_client/apis/automationjob_api.py
swagger_client/apis/build_api.py
swagger_client/apis/common_api.py
swagger_client/apis/defect_api.py
swagger_client/apis/field_api.py
swagger_client/apis/login_api.py
swagger_client/apis/module_api.py
swagger_client/apis/objectlink_api.py
swagger_client/apis/project_api.py
swagger_client/apis/release_api.py
swagger_client/apis/requirement_api.py
swagger_client/apis/search_api.py
swagger_client/apis/testcase_api.py
swagger_client/apis/testcycle_api.py
swagger_client/apis/testlog_api.py
swagger_client/apis/testrun_api.py
swagger_client/apis/testsuite_api.py
swagger_client/apis/user_api.py
swagger_client/apis/userprofile_api.py
swagger_client/models/__init__.py
swagger_client/models/admin_profile.py
swagger_client/models/allowed_value_resource.py
swagger_client/models/app_detail.py
swagger_client/models/artifact_history_resource.py
swagger_client/models/artifact_search_params.py
swagger_client/models/assigned_project.py
swagger_client/models/assigned_users_project.py
swagger_client/models/attachment_author.py
swagger_client/models/attachment_resource.py
swagger_client/models/automation_request.py
swagger_client/models/automation_schedule_creation_api.py
swagger_client/models/automation_step_log.py
swagger_client/models/automation_test_log.py
swagger_client/models/automation_test_log_resource.py
swagger_client/models/automation_test_step_log.py
swagger_client/models/build_permission.py
swagger_client/models/build_resource.py
swagger_client/models/comment_query_params.py
swagger_client/models/comment_resource.py
swagger_client/models/defect_field_mapping.py
swagger_client/models/defect_mapping.py
swagger_client/models/defect_permission.py
swagger_client/models/defect_resource.py
