Metadata-Version: 2.0
Name: rpc-qtest-swagger-client
Version: 9.1.6
Summary: qTest Manager API Version 8.6 - 9.1
Home-page: https://github.com/rcbops/qtest-swagger-client
Author: rpc-automation
Author-email: rpc-automation@rackspace.com
License: Apache Software License 2.0
Keywords: swagger qtest
Platform: UNKNOWN
Classifier: Development Status :: 5 - Production/Stable
Classifier: Intended Audience :: Developers
Classifier: License :: OSI Approved :: Apache Software License
Classifier: Natural Language :: English
Classifier: Operating System :: OS Independent
Classifier: Programming Language :: Python :: 2
Classifier: Programming Language :: Python :: 2.7
Classifier: Programming Language :: Python :: 3
Classifier: Programming Language :: Python :: 3.4
Classifier: Programming Language :: Python :: 3.5
Classifier: Programming Language :: Python :: 3.6
Classifier: Topic :: Software Development :: Libraries :: Python Modules
Requires-Dist: urllib3 (>=1.15)
Requires-Dist: six (>=1.10)
Requires-Dist: certifi
Requires-Dist: python-dateutil
